LICENSE.txt
MANIFEST.in
README.rst
requirements.txt
setup.py
finglish/__init__.py
finglish/f2p-beginning.txt
finglish/f2p-dict.txt
finglish/f2p-ending.txt
finglish/f2p-middle.txt
finglish/f2p.py
finglish/persian-word-freq.txt
finglish/version.py
finglish3.egg-info/PKG-INFO
finglish3.egg-info/SOURCES.txt
finglish3.egg-info/dependency_links.txt
finglish3.egg-info/entry_points.txt
finglish3.egg-info/top_level.txt