Metadata-Version: 1.1
Name: finglish3
Version: 1.4.8
Summary: Finglish-to-Persian converter.
Home-page: https://github.com/elektito/finglish
Author: Mostafa Razavi
Author-email: mostafa@sepent.com
License: MIT
Download-URL: https://github.com/elektito/finglish/tarball/1.4.8
Keywords: persian,finglish
Platform: UNKNOWN
Classifier: Programming Language :: Python :: 3
